utils_api_client/__init__.py
utils_api_client/api_client.py
utils_api_client/configuration.py
utils_api_client/rest.py
utils_api_client/api/__init__.py
utils_api_client/api/default_api.py
utils_api_client/models/__init__.py
utils_cli/__init__.py
utils_cli/api_token.py
utils_cli/dnscheck.py
utils_cli/google.py
utils_cli/netidcheck.py
utils_cli/util.py
oss_utils_cli-0.0.3.dist-info/METADATA
oss_utils_cli-0.0.3.dist-info/WHEEL
oss_utils_cli-0.0.3.dist-info/entry_points.txt
oss_utils_cli-0.0.3.dist-info/top_level.txt
oss_utils_cli-0.0.3.dist-info/RECORD
